security_arbihacker/__init__.py
security_arbihacker/prefixed_security.py
security_arbihacker-0.1.1.dist-info/METADATA
security_arbihacker-0.1.1.dist-info/WHEEL
security_arbihacker-0.1.1.dist-info/licenses/LICENSE
security_arbihacker-0.1.1.dist-info/RECORD
