Metadata-Version: 2.1
Name: security-arbihacker
Version: 0.1.1
Summary: Utils to make setting up API security with FastAPI faster and easier.
Project-URL: Homepage, https://github.com/ArbiHacker/security_arbihacker
Author-email: Sergei Aslamazov <mrvisioo@gmail.com>
License-File: LICENSE
Classifier: License :: OSI Approved :: MIT License
Classifier: Operating System :: OS Independent
Classifier: Programming Language :: Python :: 3
Requires-Python: >=3.10
Requires-Dist: fastapi~=0.96.0
Requires-Dist: python-jose[cryptography]~=3.3.0
